pycryptostring.py
pycryptostring-1.0.0.dist-info/LICENSE
pycryptostring-1.0.0.dist-info/METADATA
pycryptostring-1.0.0.dist-info/WHEEL
pycryptostring-1.0.0.dist-info/top_level.txt
pycryptostring-1.0.0.dist-info/RECORD
