Metadata-Version: 2.1
Name: pycryptostring
Version: 1.0.0
Summary: A text format for easily interacting with cryptographic hashes and keys
Home-page: https://github.com/darkwyrm/pycryptostring
Author: Jon Yoder
Author-email: jon@yoder.cloud
License: MIT
Project-URL: Bug Tracker, https://github.com/darkwyrm/pycryptostring/issues
Platform: UNKNOWN
Classifier: Development Status :: 5 - Production/Stable
Classifier: Intended Audience :: Developers
Classifier: Topic :: Software Development
Classifier: Programming Language :: Python
Classifier: License :: OSI Approved :: MIT License
Classifier: Operating System :: OS Independent
License-File: LICENSE
Requires-Dist: retval (>=1.0.0)
